termplots/__init__.py
termplots-0.2.1.dist-info/LICENSE
termplots-0.2.1.dist-info/METADATA
termplots-0.2.1.dist-info/WHEEL
termplots-0.2.1.dist-info/top_level.txt
termplots-0.2.1.dist-info/RECORD
