Metadata-Version: 2.1
Name: termplots
Version: 0.2.1
Summary: A lightweight plot library for your terminal!
Author-email: Lorenzo Andreasi <lolloandreasi@gmail.com>
Project-URL: Homepage, https://github.com/lollo03/termplots
Classifier: Programming Language :: Python :: 3
Classifier: License :: OSI Approved :: MIT License
Classifier: Operating System :: OS Independent
Requires-Python: >=3.7
License-File: LICENSE
